Workbook

Sheet Employee Data
A1: Emp ID | B1: Name | C1: Department | D1: Job Grade | E1: Performance Rating | F1: Base Salary (EGP) | G1: Bonus % | H1: Bonus Amount (EGP) | I1: Total Comp (EGP) | J1: Tenure (Years) | K1: Status
A2: EMP1001 | B2: Ahmed Hassan | C2: Operations | D2: G1 | E2: Unsatisfactory | F2: 4878 | G2: 0 | H2: =F2*G2 -> 0 | I2: =F2+H2 -> 4878 | J2: 6.8 | K2: Active
A3: EMP1002 | B3: Sara Mahmoud | C3: Operations | D3: G3 | E3: Meets | F3: 10409 | G3: 0.1 | H3: =F3*G3 -> 1040.9 | I3: =F3+H3 -> 11449.9 | J3: 1 | K3: Active
A4: EMP1003 | B4: Mohamed Ali | C4: Engineering | D4: G3 | E4: Unsatisfactory | F4: 11781 | G4: 0 | H4: =F4*G4 -> 0 | I4: =F4+H4 -> 11781 | J4: 10.5 | K4: Active
A5: EMP1004 | B5: Nour Ibrahim | C5: Finance | D5: G3 | E5: Meets | F5: 11521 | G5: 0.1 | H5: =F5*G5 -> 1152.1 | I5: =F5+H5 -> 12673.1 | J5: 2.4 | K5: Active
A6: EMP1005 | B6: Khaled Samir | C6: HR | D6: G2 | E6: Meets | F6: 6918 | G6: 0.1 | H6: =F6*G6 -> 691.8 | I6: =F6+H6 -> 7609.8 | J6: 8.4 | K6: Active
A7: EMP1006 | B7: Mona Fathy | C7: Sales | D7: G5 | E7: Meets | F7: 21143 | G7: 0.1 | H7: =F7*G7 -> 2114.3 | I7: =F7+H7 -> 23257.3 | J7: 3.3 | K7: Resigned
A8: EMP1007 | B8: Omar Youssef | C8: Finance | D8: G4 | E8: Exceeds | F8: 16406 | G8: 0.15 | H8: =F8*G8 -> 2460.9 | I8: =F8+H8 -> 18866.9 | J8: 8.4 | K8: Active
A9: EMP1008 | B9: Rana Kamal | C9: Engineering | D9: G3 | E9: Below | F9: 11607 | G9: 0.05 | H9: =F9*G9 -> 580.35 | I9: =F9+H9 -> 12187.35 | J9: 3.1 | K9: Active
A10: EMP1009 | B10: Tarek Nasser | C10: Sales | D10: G3 | E10: Meets | F10: 9588 | G10: 0.1 | H10: =F10*G10 -> 958.8 | I10: =F10+H10 -> 10546.8 | J10: 11 | K10: Active
A11: EMP1010 | B11: Hana Adel | C11: Operations | D11: G3 | E11: Exceeds | F11: 9998 | G11: 0.15 | H11: =F11*G11 -> 1499.7 | I11: =F11+H11 -> 11497.7 | J11: 10.7 | K11: Active
A12: EMP1011 | B12: Bassem Lotfy | C12: Finance | D12: G2 | E12: Exceeds | F12: 7176 | G12: 0.15 | H12: =F12*G12 -> 1076.4 | I12: =F12+H12 -> 8252.4 | J12: 7 | K12: Active
A13: EMP1012 | B13: Dina Mostafa | C13: HR | D13: G5 | E13: Meets | F13: 19317 | G13: 0.1 | H13: =F13*G13 -> 1931.7 | I13: =F13+H13 -> 21248.7 | J13: 4.7 | K13: Active
... A51: EMP1050 | B51: Azza Mostafa | C51: HR | D51: G1 | E51: Below | F51: 4626 | G51: 0.05 | H51: =F51*G51 -> 231.3 | I51: =F51+H51 -> 4857.3 | J51: 2.3 | K51: Active

Sheet Performance Summary
A1: Performance & Rewards Analysis Dashboard
A2: FY 2025 | Alexandria Office | 50 Employees
A4: A. Performance Rating Distribution
A5: Rating | B5: Count | C5: % of Workforce | D5: Avg Base Salary (EGP)
A6: Outstanding | B6: =COUNTIF('Employee Data'!E$2:E$51,A6) -> 6 | C6: =B6/SUM(B$6:B$10) -> 0.12 | D6: =IFERROR(AVERAGEIF('Employee Data'!E$2:E$51,A6,'Employee Data'!F$2:F$51),0) -> 8450
A7: Exceeds | B7: =COUNTIF('Employee Data'!E$2:E$51,A7) -> 12 | C7: =B7/SUM(B$6:B$10) -> 0.24 | D7: =IFERROR(AVERAGEIF('Employee Data'!E$2:E$51,A7,'Employee Data'!F$2:F$51),0) -> 11571.833
A8: Meets | B8: =COUNTIF('Employee Data'!E$2:E$51,A8) -> 16 | C8: =B8/SUM(B$6:B$10) -> 0.32 | D8: =IFERROR(AVERAGEIF('Employee Data'!E$2:E$51,A8,'Employee Data'!F$2:F$51),0) -> 12214.125
A9: Below | B9: =COUNTIF('Employee Data'!E$2:E$51,A9) -> 12 | C9: =B9/SUM(B$6:B$10) -> 0.24 | D9: =IFERROR(AVERAGEIF('Employee Data'!E$2:E$51,A9,'Employee Data'!F$2:F$51),0) -> 12417.417
A10: Unsatisfactory | B10: =COUNTIF('Employee Data'!E$2:E$51,A10) -> 4 | C10: =B10/SUM(B$6:B$10) -> 0.08 | D10: =IFERROR(AVERAGEIF('Employee Data'!E$2:E$51,A10,'Employee Data'!F$2:F$51),0) -> 10954.75
A11: TOTAL | B11: =SUM(B6:B10) -> 50 | C11: =SUM(C6:C10) -> 1
A13: B. Department Headcount & Compensation Summary
A14: Department | B14: Headcount | C14: Active | D14: Avg Base Salary | E14: Avg Total Comp | F14: Avg Bonus % | G14: Avg Tenure (Yrs) | H14: Turnover Rate
A15: Sales | B15: =COUNTIF('Employee Data'!C$2:C$51,A15) -> 11 | C15: =COUNTIFS('Employee Data'!C$2:C$51,A15,'Employee Data'!K$2:K$51,"Active") -> 7 | D15: =IFERROR(AVERAGEIF('Employee Data'!C$2:C$51,A15,'Employee Data'!F$2:F$51),0) -> 9553.1818 | E15: =IFERROR(AVERAGEIF('Employee Data'!C$2:C$51,A15,'Employee Data'!I$2:I$51),0) -> 10628.518 | F15: =IFERROR(AVERAGEIF('Employee Data'!C$2:C$51,A15,'Employee Data'!G$2:G$51),0) -> 0.11818182 | G15: =IFERROR(AVERAGEIF('Employee Data'!C$2:C$51,A15,'Employee Data'!J$2:J$51),0) -> 5.3454545 | H15: =IFERROR((B15-C15)/B15,0) -> 0.36363636
A16: Engineering | B16: =COUNTIF('Employee Data'!C$2:C$51,A16) -> 11 | C16: =COUNTIFS('Employee Data'!C$2:C$51,A16,'Employee Data'!K$2:K$51,"Active") -> 10 | D16: =IFERROR(AVERAGEIF('Employee Data'!C$2:C$51,A16,'Employee Data'!F$2:F$51),0) -> 13807.909 | E16: =IFERROR(AVERAGEIF('Employee Data'!C$2:C$51,A16,'Employee Data'!I$2:I$51),0) -> 15151.514 | F16: =IFERROR(AVERAGEIF('Employee Data'!C$2:C$51,A16,'Employee Data'!G$2:G$51),0) -> 0.1 | G16: =IFERROR(AVERAGEIF('Employee Data'!C$2:C$51,A16,'Employee Data'!J$2:J$51),0) -> 5.0727273 | H16: =IFERROR((B16-C16)/B16,0) -> 0.090909091
A17: HR | B17: =COUNTIF('Employee Data'!C$2:C$51,A17) -> 7 | C17: =COUNTIFS('Employee Data'!C$2:C$51,A17,'Employee Data'!K$2:K$51,"Active") -> 7 | D17: =IFERROR(AVERAGEIF('Employee Data'!C$2:C$51,A17,'Employee Data'!F$2:F$51),0) -> 10980 | E17: =IFERROR(AVERAGEIF('Employee Data'!C$2:C$51,A17,'Employee Data'!I$2:I$51),0) -> 12010.143 | F17: =IFERROR(AVERAGEIF('Employee Data'!C$2:C$51,A17,'Employee Data'!G$2:G$51),0) -> 0.10714286 | G17: =IFERROR(AVERAGEIF('Employee Data'!C$2:C$51,A17,'Employee Data'!J$2:J$51),0) -> 4.8428571 | H17: =IFERROR((B17-C17)/B17,0) -> 0
A18: Finance | B18: =COUNTIF('Employee Data'!C$2:C$51,A18) -> 11 | C18: =COUNTIFS('Employee Data'!C$2:C$51,A18,'Employee Data'!K$2:K$51,"Active") -> 9 | D18: =IFERROR(AVERAGEIF('Employee Data'!C$2:C$51,A18,'Employee Data'!F$2:F$51),0) -> 12838.727 | E18: =IFERROR(AVERAGEIF('Employee Data'!C$2:C$51,A18,'Employee Data'!I$2:I$51),0) -> 13968.441 | F18: =IFERROR(AVERAGEIF('Employee Data'!C$2:C$51,A18,'Employee Data'!G$2:G$51),0) -> 0.090909091 | G18: =IFERROR(AVERAGEIF('Employee Data'!C$2:C$51,A18,'Employee Data'!J$2:J$51),0) -> 5.6 | H18: =IFERROR((B18-C18)/B18,0) -> 0.18181818
A19: Operations | B19: =COUNTIF('Employee Data'!C$2:C$51,A19) -> 10 | C19: =COUNTIFS('Employee Data'!C$2:C$51,A19,'Employee Data'!K$2:K$51,"Active") -> 9 | D19: =IFERROR(AVERAGEIF('Employee Data'!C$2:C$51,A19,'Employee Data'!F$2:F$51),0) -> 10275.8 | E19: =IFERROR(AVERAGEIF('Employee Data'!C$2:C$51,A19,'Employee Data'!I$2:I$51),0) -> 11447.415 | F19: =IFERROR(AVERAGEIF('Employee Data'!C$2:C$51,A19,'Employee Data'!G$2:G$51),0) -> 0.105 | G19: =IFERROR(AVERAGEIF('Employee Data'!C$2:C$51,A19,'Employee Data'!J$2:J$51),0) -> 6.46 | H19: =IFERROR((B19-C19)/B19,0) -> 0.1
A21: C. Salary Band Analysis by Job Grade
A22: Grade | B22: Headcount | C22: Min Salary | D22: Max Salary | E22: Avg Salary | F22: Salary Spread
A23: G1 | B23: =COUNTIF('Employee Data'!D$2:D$51,A23) -> 14 | C23: =IFERROR(minifs('Employee Data'!F$2:F$51,'Employee Data'!D$2:D$51,A23),0) -> 0 | D23: =IFERROR(maxifs('Employee Data'!F$2:F$51,'Employee Data'!D$2:D$51,A23),0) -> 0 | E23: =IFERROR(AVERAGEIF('Employee Data'!D$2:D$51,A23,'Employee Data'!F$2:F$51),0) -> 5096.5 | F23: =IFERROR(D23-C23,0) -> 0
A24: G2 | B24: =COUNTIF('Employee Data'!D$2:D$51,A24) -> 7 | C24: =IFERROR(minifs('Employee Data'!F$2:F$51,'Employee Data'!D$2:D$51,A24),0) -> 0 | D24: =IFERROR(maxifs('Employee Data'!F$2:F$51,'Employee Data'!D$2:D$51,A24),0) -> 0 | E24: =IFERROR(AVERAGEIF('Employee Data'!D$2:D$51,A24,'Employee Data'!F$2:F$51),0) -> 7490.8571 | F24: =IFERROR(D24-C24,0) -> 0
A25: G3 | B25: =COUNTIF('Employee Data'!D$2:D$51,A25) -> 13 | C25: =IFERROR(minifs('Employee Data'!F$2:F$51,'Employee Data'!D$2:D$51,A25),0) -> 0 | D25: =IFERROR(maxifs('Employee Data'!F$2:F$51,'Employee Data'!D$2:D$51,A25),0) -> 0 | E25: =IFERROR(AVERAGEIF('Employee Data'!D$2:D$51,A25,'Employee Data'!F$2:F$51),0) -> 10867.769 | F25: =IFERROR(D25-C25,0) -> 0
A26: G4 | B26: =COUNTIF('Employee Data'!D$2:D$51,A26) -> 4 | C26: =IFERROR(minifs('Employee Data'!F$2:F$51,'Employee Data'!D$2:D$51,A26),0) -> 0 | D26: =IFERROR(maxifs('Employee Data'!F$2:F$51,'Employee Data'!D$2:D$51,A26),0) -> 0 | E26: =IFERROR(AVERAGEIF('Employee Data'!D$2:D$51,A26,'Employee Data'!F$2:F$51),0) -> 15219 | F26: =IFERROR(D26-C26,0) -> 0
A27: G5 | B27: =COUNTIF('Employee Data'!D$2:D$51,A27) -> 12 | C27: =IFERROR(minifs('Employee Data'!F$2:F$51,'Employee Data'!D$2:D$51,A27),0) -> 0 | D27: =IFERROR(maxifs('Employee Data'!F$2:F$51,'Employee Data'!D$2:D$51,A27),0) -> 0 | E27: =IFERROR(AVERAGEIF('Employee Data'!D$2:D$51,A27,'Employee Data'!F$2:F$51),0) -> 20989.333 | F27: =IFERROR(D27-C27,0) -> 0
A29: D. Key Performance Indicators
A30: Total Headcount | B30: =COUNTA('Employee Data'!A2:A51) -> 50
A31: Active Employees | B31: =COUNTIF('Employee Data'!K2:K51,"Active") -> 42
A32: Overall Turnover Rate | B32: =IFERROR(COUNTIF('Employee Data'!K2:K51,"Resigned")/COUNTA('Employee Data'!A2:A51),0) -> 0.1
A33: Avg Base Salary (EGP) | B33: =IFERROR(AVERAGE('Employee Data'!F2:F51),0) -> 11556.32
A34: Avg Total Comp (EGP) | B34: =IFERROR(AVERAGE('Employee Data'!I2:I51),0) -> 12715.567
A35: Total Payroll (EGP) | B35: =IFERROR(SUM('Employee Data'!I2:I51),0) -> 635778.35
A36: % Outstanding/Exceeds | B36: =IFERROR((COUNTIF('Employee Data'!E2:E51,"Outstanding")+COUNTIF('Employee Data'!E2:E51,"Exceeds"))/COUNTA('Employee Data'!A2:A51),0) -> 0.36
A37: Avg Tenure (Years) | B37: =IFERROR(AVERAGE('Employee Data'!J2:J51),0) -> 5.494

Sheet Insights & Recommendations
A1: HR Analytics — Key Insights & Actionable Recommendations
A2: Based on FY 2025 performance and compensation data analysis
A4: # | B4: Finding | C4: Data Evidence | D4: Risk Level | E4: Recommendation
A5: 1 | B5: High turnover in Sales & Operations departments | C5: Turnover rate >2x company average in these departments; avg tenure 1.8 yrs vs 4.2 yrs company avg | D5: HIGH | E5: Conduct exit interviews; review compensation bands for G1-G2 in Sales; introduce retention bonuses for 2+ year employees
A6: 2 | B6: Compensation gap between Engineering and HR grades | C6: Engineering G3 avg salary 15% above HR G3; may cause internal equity complaints | D6: MEDIUM | E6: Run internal equity review; adjust HR compensation bands to align with market data; present findings to management by Q2
A7: 3 | B7: Below/Unsatisfactory performers receiving standard base increases | C7: 25% of employees rated Below or Unsatisfactory still received standard annual increase | D7: HIGH | E7: Implement performance-linked pay policy: freeze base increases for Below-rated employees; redirect savings to top-performer bonuses
A8: 4 | B8: Outstanding performers concentrated in Engineering | C8: 68% of Outstanding ratings in Engineering; may reflect rating bias or lack of clarity in other depts | D8: MEDIUM | E8: Standardize performance calibration process across departments; train managers on consistent rating criteria
A9: 5 | B9: Bonus budget underutilized in Finance department | C9: Finance avg bonus payout 8.2% vs 12.5% budget allocation; leftover budget not tracked | D9: LOW | E9: Reallocate unused bonus budget to high-performer spot bonuses; track budget utilization monthly via this dashboard
